pikados/__init__.py
pikados/channel.py
pikados/connection.py
pikados/futures.py
pikados-0.1.0.dist-info/METADATA
pikados-0.1.0.dist-info/WHEEL
pikados-0.1.0.dist-info/RECORD
